app/__init__.py
app/main.py
app/handlers/__init__.py
app/handlers/generate/__init__.py
app/handlers/generate/backend.py
app/handlers/generate/frontend.py
app/resources/__init__.py
app/resources/chakra.py
app/resources/redux.py
app/resources/router.py
app/resources/tailwind.py
app/resources/utils.py
hades_cli-0.0.13.dist-info/METADATA
hades_cli-0.0.13.dist-info/WHEEL
hades_cli-0.0.13.dist-info/entry_points.txt
hades_cli-0.0.13.dist-info/top_level.txt
hades_cli-0.0.13.dist-info/RECORD
